mbta_mcp/__init__.py
mbta_mcp/_version.py
mbta_mcp/cli.py
mbta_mcp/client.py
mbta_mcp/extended_client.py
mbta_mcp/fuzzy_filter.py
mbta_mcp/server.py
mbta_mcp-1.1.1.dist-info/METADATA
mbta_mcp-1.1.1.dist-info/WHEEL
mbta_mcp-1.1.1.dist-info/entry_points.txt
mbta_mcp-1.1.1.dist-info/licenses/LICENSE
mbta_mcp-1.1.1.dist-info/RECORD
