Metadata-Version: 2.4
Name: mbta-mcp
Version: 1.1.1
Summary: MCP server for MBTA V3 API
Project-URL: Homepage, https://github.com/cubismod/mbta-mcp
Project-URL: Repository, https://github.com/cubismod/mbta-mcp.git
Project-URL: Issues, https://github.com/cubismod/mbta-mcp/issues
Author-email: Ryan Wallace <ryan@hexa.mozmail.com>
License: Apache-2.0
License-File: LICENSE
Keywords: api,boston,mbta,mcp,transit
Classifier: Development Status :: 4 - Beta
Classifier: Intended Audience :: Developers
Classifier: License :: OSI Approved :: Apache Software License
Classifier: Programming Language :: Python :: 3
Classifier: Programming Language :: Python :: 3.11
Classifier: Programming Language :: Python :: 3.12
Classifier: Programming Language :: Python :: 3.13
Classifier: Topic :: Internet :: WWW/HTTP :: Dynamic Content
Classifier: Topic :: Software Development :: Libraries :: Python Modules
Requires-Python: <4.0,>=3.11
Requires-Dist: aiohttp>=3.12.14
Requires-Dist: async-lru>=2.0.5
Requires-Dist: cachetools>=5.3.0
Requires-Dist: click>=8.0.0
Requires-Dist: mcp>=1.0.0
Requires-Dist: pydantic>=2.11.7
Requires-Dist: python-dotenv>=1.0.0
Requires-Dist: tenacity>=9.0.0
Requires-Dist: types-cachetools>=4.2.0
